{
    "channel": {
        "active": true, 
        "adult": false, 
        "category": [
            "serie", 
            "vos"
        ], 
        "changes": "Arreglado la sección findVideos de seriesblanco", 
        "date": "28/03/2016", 
        "fanart": "", 
        "id": "seriesblanco", 
        "include_in_global_search": false, 
        "language": "es", 
        "name": "Seriesblanco", 
        "thumbnail": "", 
        "update_url": "", 
        "version": "10.0"
    }, 
    "settings": {}
}
